{
  "title": "Why Your Brain Is Addicted to Bad News",
  "lines": [
    {
      "id": 1,
      "text": "You open your phone to check the time — and 20 minutes later you're still scrolling bad news.",
      "image_keyword": "person scrolling phone in bed at night"
    },
    {
      "id": 2,
      "text": "This isn't a willpower problem. Your brain is literally wired for it.",
      "image_keyword": "frustrated woman staring at phone"
    },
    {
      "id": 3,
      "text": "It's called negativity bias — your brain processes threats faster and stronger than good news.",
      "image_keyword": "stressed person reading bad news"
    },
    {
      "id": 4,
      "text": "For thousands of years, missing a threat meant death. Missing good news just meant a missed opportunity.",
      "image_keyword": "ancient cave painting prehistoric"
    },
    {
      "id": 5,
      "text": "So your brain evolved to prioritize danger. Bad news feels more real, more urgent, more important.",
      "image_keyword": "worried man reading newspaper headlines"
    },
    {
      "id": 6,
      "text": "Social media platforms learned this too — negative posts get more clicks, more shares, more time on screen.",
      "image_keyword": "person addicted to phone scrolling social media"
    },
    {
      "id": 7,
      "text": "The result: your ancient survival brain is being hijacked by an algorithm designed to keep you anxious.",
      "image_keyword": "anxious person alone in dark room"
    },
    {
      "id": 8,
      "text": "Knowing this doesn't fix it — but it gives you the one thing the algorithm doesn't want you to have: awareness.",
      "image_keyword": "calm person meditating outdoors at sunrise"
    }
  ]
}
